gitcrawl/__init__.py
gitcrawl/core_functions.py
gitcrawl/deprecated.py
gitcrawl/generate_python_module_list.py
gitcrawl/gitcrawl.py
gitcrawl/helpers.py
gitcrawl/module-names.txt
gitcrawl/python_module_index.pickle
gitcrawl-0.1.3.dist-info/LICENSE
gitcrawl-0.1.3.dist-info/METADATA
gitcrawl-0.1.3.dist-info/WHEEL
gitcrawl-0.1.3.dist-info/entry_points.txt
gitcrawl-0.1.3.dist-info/top_level.txt
gitcrawl-0.1.3.dist-info/RECORD
