Metadata-Version: 2.1
Name: gitcrawl
Version: 0.1.3
Summary: A small package for creating os-agnostic conda environment.yml files
Home-page: https://github.com/nsultova/gitcrawl
Author: Neda Sultova
Author-email: n.sultova@hzdr.de
License: UNKNOWN
Platform: UNKNOWN
Classifier: Programming Language :: Python :: 3
Classifier: License :: OSI Approved :: MIT License
Classifier: Operating System :: OS Independent
Requires-Python: >=3.6
Requires-Dist: beautifulsoup4
Requires-Dist: tqdm
Requires-Dist: requests
Requires-Dist: PyYAML
Requires-Dist: requirements-parser
Requires-Dist: pip-search (>=0.0.6)
Requires-Dist: findimports
